which_animal_demo/which_animal.py
which_animal_demo-0.1.0.dist-info/METADATA
which_animal_demo-0.1.0.dist-info/WHEEL
which_animal_demo-0.1.0.dist-info/entry_points.txt
which_animal_demo-0.1.0.dist-info/RECORD
