Metadata-Version: 2.1
Name: which-animal-demo
Version: 0.1.0
Summary: 
Author: the
Author-email: the@illumina.com
Requires-Python: >=3.12,<4.0
Classifier: Programming Language :: Python :: 3
Classifier: Programming Language :: Python :: 3.12
Requires-Dist: lunardate (>=0.1.5,<0.2.0)
